pyfbook/FacebookReport.py
pyfbook/SystemUser.py
pyfbook/__init__.py
pyfbook/core/__init__.py
pyfbook/core/ad_accounts/__init__.py
pyfbook/core/ad_accounts/ad_accounts.py
pyfbook/core/ad_accounts/init_connector.py
pyfbook/core/config/__init__.py
pyfbook/core/marketing/__init__.py
pyfbook/core/marketing/extract/__init__.py
pyfbook/core/marketing/extract/api.py
pyfbook/core/marketing/extract/date.py
pyfbook/core/marketing/extract/filters.py
pyfbook/core/marketing/extract/params.py
pyfbook/core/marketing/extract/start_update_date.py
pyfbook/core/marketing/extract/reports/__init__.py
pyfbook/core/marketing/extract/reports/launch.py
pyfbook/core/marketing/extract/reports/save.py
pyfbook/core/marketing/transform_and_load/__init__.py
pyfbook/core/marketing/transform_and_load/fetch.py
pyfbook-0.3.20.dist-info/METADATA
pyfbook-0.3.20.dist-info/WHEEL
pyfbook-0.3.20.dist-info/top_level.txt
pyfbook-0.3.20.dist-info/RECORD
