Metadata-Version: 2.1
Name: pyfbook
Version: 0.3.20
Summary: Easily collect data from Facebook APIs
Home-page: UNKNOWN
License: UNKNOWN
Keywords: collect data facebook api
Platform: UNKNOWN
Requires-Python: >=3
Requires-Dist: dbstream (>=0.0.14)
Requires-Dist: PyYAML (>=5.1)
